README
setup.cfg
setup.py
miftpclient/__init__.py
miftpclient/ftpclient.py
miftpclient/ipparser.py
miftpclient/main.py
miftpclient/scan.py
miftpclient.egg-info/PKG-INFO
miftpclient.egg-info/SOURCES.txt
miftpclient.egg-info/dependency_links.txt
miftpclient.egg-info/entry_points.txt
miftpclient.egg-info/requires.txt
miftpclient.egg-info/top_level.txt