Metadata-Version: 1.0
Name: miftpclient
Version: 0.5
Summary: connect to your xiaomi phone's ftp server automatically.
Home-page: UNKNOWN
Author: cong liu
Author-email: shishusaiwai@vip.qq.com
License: GPL
Platform: UNKNOWN
